hydrobotdbc/__init__.py
hydrobotdbc/client.py
hydrobotdbc/models/__init__.py
hydrobotdbc/models/bet.py
hydrobotdbc/models/collection.py
hydrobotdbc/models/daily_claim.py
hydrobotdbc/models/game.py
hydrobotdbc/models/poll.py
hydrobotdbc/models/user.py
hydrobotdbc/models/user_birthday.py
hydrobotdbc/models/user_seed.py
hydrobotdbc/models/user_session.py
hydrobotdbc/models/user_voicestate.py
hydrobotdbc/models/user_wallet.py
hydrobotdbc/models/wallet.py
hydrobotdbc-0.0.18.dist-info/METADATA
hydrobotdbc-0.0.18.dist-info/WHEEL
hydrobotdbc-0.0.18.dist-info/top_level.txt
hydrobotdbc-0.0.18.dist-info/RECORD
