Metadata-Version: 2.1
Name: hydrobotdbc
Version: 0.0.18
Summary: A custom Pyodbc wrapper
Author: Daniel Ferrer
Author-email: ferrdan2506@hotmail.com
Requires-Dist: pyodbc
Requires-Dist: python-dotenv
Requires-Dist: flask-login
Requires-Dist: twine
